Metadata-Version: 2.1
Name: colab-repoclone
Version: 0.1.4
Summary: Code for integrating git push/pull capabilities into Google Colab
Home-page: UNKNOWN
Author: JordanLueck
Author-email: jordan.lueck@apolitical.co
License: UNKNOWN
Download-URL: https://github.com/apolitical/colab_repoclone/archive/v0.1.4.tar.gz
Platform: UNKNOWN
